<?xml version="1.0" encoding="utf-8"?>
<!DOCTYPE hibernate-mapping PUBLIC "-//Hibernate/Hibernate Mapping DTD 3.0//EN"
"http://hibernate.sourceforge.net/hibernate-mapping-3.0.dtd">
<!-- 
    Mapping file autogenerated by MyEclipse Persistence Tools
-->
<hibernate-mapping>
    <class name="com.sosgps.wzt.orm.TAreaLocrecord" table="T_AREA_LOCRECORD" schema="MAPSEARCH" dynamic-insert="true">
        <id name="id" type="java.lang.Long">
            <column name="ID" precision="22" scale="0" />
            <generator class="sequence">
            	<param name="sequence">SEQ_AREALARM_LOCRECORD</param>
            </generator>
        </id>
        <property name="deviceId" type="java.lang.String">
            <column name="DEVICE_ID" length="50" />
        </property>
        <property name="longitude" type="java.lang.Float">
            <column name="LONGITUDE" precision="126" scale="0" />
        </property>
        <property name="latitude" type="java.lang.Float">
            <column name="LATITUDE" precision="126" scale="0" />
        </property>
        <property name="jmx" type="java.lang.String">
            <column name="JMX" length="20" />
        </property>
        <property name="jmy" type="java.lang.String">
            <column name="JMY" length="20" />
        </property>
        <property name="speed" type="java.lang.Float">
            <column name="SPEED" precision="126" scale="0" />
        </property>
        <property name="direction" type="java.lang.Float">
            <column name="DIRECTION" precision="126" scale="0" />
        </property>
        <property name="height" type="java.lang.Float">
            <column name="HEIGHT" precision="126" scale="0" />
        </property>
        <property name="distance" type="java.lang.Float">
            <column name="DISTANCE" precision="126" scale="0" />
        </property>
        <property name="statlliteNum" type="java.lang.Long">
            <column name="STATLLITE_NUM" precision="22" scale="0" />
        </property>
        <property name="alarmTime" type="java.util.Date">
            <column name="ALARM_TIME" length="7" />
        </property>
        <property name="alarmType" type="java.lang.String">
            <column name="ALARM_TYPE" length="1" />
        </property>
        <property name="inputdate" type="java.util.Date">
            <column name="INPUTDATE" length="7" />
        </property>
        <property name="caseId" type="java.lang.Long">
            <column name="CASE_ID" precision="22" scale="0" />
        </property>
        <property name="calledNumber" type="java.lang.String">
            <column name="CALLED_NUMBER" length="50" />
        </property>
        <property name="entCode" type="java.lang.String">
            <column name="ENT_CODE" length="50" />
        </property>
        <property name="areaPoints" type="java.lang.String">
            <column name="AREA_POINTS" length="500" />
        </property>
        <property name="startTime" type="java.lang.String">
            <column name="START_TIME" length="5" />
        </property>
        <property name="endTime" type="java.lang.String">
            <column name="END_TIME" length="5" />
        </property>
        <property name="areaType" type="java.lang.String">
            <column name="AREA_TYPE" length="1" />
        </property>
        <property name="speedLimit" type="java.lang.Long">
            <column name="SPEED_LIMIT"  precision="22" scale="0" />
        </property>
        <property name="locDesc" type="java.lang.String">
            <column name="LOC_DESC" length="500" />
        </property>
    </class>
</hibernate-mapping>
