<?xml version="1.0" encoding="utf-8"?>
<!DOCTYPE hibernate-mapping PUBLIC "-//Hibernate/Hibernate Mapping DTD 3.0//EN"
"http://hibernate.sourceforge.net/hibernate-mapping-3.0.dtd">
<!-- 
    Mapping file autogenerated by MyEclipse - Hibernate Tools
-->
<hibernate-mapping>
    <class name="com.sosgps.wzt.orm.TLoginLog" table="T_LOGIN_LOG"   dynamic-insert="true" >
        <id name="id" type="java.lang.Long">
            <column name="ID" precision="22" scale="0" />
            <generator class="sequence">
				<param name="sequence">SEQ_LOGIN_LOG</param>
			</generator>
        </id>
        <property name="userId" type="java.lang.Long">
            <column name="USER_ID" precision="22" scale="0" not-null="true" />
        </property>
        <property name="userName" type="java.lang.String">
            <column name="USER_NAME" length="100" not-null="true" />
        </property>
        <property name="empCode" type="java.lang.String">
            <column name="EMP_CODE" length="20"  not-null="true" />
        </property>
        <property name="accessIp" type="java.lang.String">
            <column name="ACCESS_IP" length="20" not-null="true" />
        </property>
        <property name="loginTime" type="java.util.Date">
            <column name="LOGIN_TIME" length="7" />
        </property>
        <property name="loginDesc" type="java.lang.String">
            <column name="LOGIN_DESC" length="100" />
        </property>
        <property name="result" type="java.lang.Long">
            <column name="RESULT" precision="22" scale="0" not-null="true" />
        </property>
    </class>
</hibernate-mapping>
